tomorrow_io/__init__.py
tomorrow_io/tomorrow.py
tomorrow_io-0.0.3.dist-info/LICENSE
tomorrow_io-0.0.3.dist-info/METADATA
tomorrow_io-0.0.3.dist-info/WHEEL
tomorrow_io-0.0.3.dist-info/top_level.txt
tomorrow_io-0.0.3.dist-info/RECORD
